extreme/cleanup.py
extreme/__init__.py
extreme/testcase.py
django_extreme_tdd-0.1.0.dist-info/METADATA
django_extreme_tdd-0.1.0.dist-info/top_level.txt
django_extreme_tdd-0.1.0.dist-info/metadata.json
django_extreme_tdd-0.1.0.dist-info/DESCRIPTION.rst
django_extreme_tdd-0.1.0.dist-info/WHEEL
django_extreme_tdd-0.1.0.dist-info/RECORD
