Metadata-Version: 2.0
Name: django-extreme-tdd
Version: 0.1.0
Summary: Testing toolkit to advocate real and fast TDD (testing first!) in Django applications, eXtremeProgramming like!
Home-page: https://github.com/flaviamissi/django-extreme-tdd
Author: Flavia Missi
Author-email: flaviamissi@gmail.com
License: BSD
Keywords: testing tdd development django
Platform: UNKNOWN
Classifier: Development Status :: 3 - Alpha
Classifier: Intended Audience :: Developers
Classifier: Topic :: Software Development :: Testing Tools
Classifier: License :: OSI Approved :: BSD License
Classifier: Programming Language :: Python :: 2.6
Classifier: Programming Language :: Python :: 2.7
Requires-Dist: django (>=1.4)
Provides-Extra: dev
Requires-Dist: mkdocs; extra == 'dev'
Provides-Extra: test
Requires-Dist: nose; extra == 'test'
